factorial2kr/__init__.py
factorial2kr/factorial.py
factorial2kr/factorial_data.py
factorial2kr-0.1.7.dist-info/METADATA
factorial2kr-0.1.7.dist-info/WHEEL
factorial2kr-0.1.7.dist-info/RECORD
