Metadata-Version: 2.3
Name: factorial2kr
Version: 0.1.7
Summary: Lib for 2kr factorial projects
License: GPL-3.0
Author: Kyamel
Author-email: lcamelo200@gmail.com
Requires-Python: >=3.11
Classifier: License :: OSI Approved :: GNU General Public License v3 (GPLv3)
Classifier: Programming Language :: Python :: 3
Classifier: Programming Language :: Python :: 3.11
Classifier: Programming Language :: Python :: 3.12
Classifier: Programming Language :: Python :: 3.13
Requires-Dist: numpy (>=2.3.2,<3.0.0)
Requires-Dist: scipy (>=1.16.1,<2.0.0)
